koder_agent/__init__.py
koder_agent/cli.py
koder_agent/agentic/__init__.py
koder_agent/agentic/agent.py
koder_agent/agentic/approval_hooks.py
koder_agent/agentic/hooks.py
koder_agent/agentic/skill_guardrail.py
koder_agent/auth/__init__.py
koder_agent/auth/base.py
koder_agent/auth/callback_server.py
koder_agent/auth/cli_handler.py
koder_agent/auth/client_integration.py
koder_agent/auth/codex_prompts.py
koder_agent/auth/constants.py
koder_agent/auth/litellm_oauth.py
koder_agent/auth/token_storage.py
koder_agent/auth/tool_utils.py
koder_agent/auth/providers/__init__.py
koder_agent/auth/providers/antigravity.py
koder_agent/auth/providers/chatgpt.py
koder_agent/auth/providers/claude.py
koder_agent/auth/providers/google.py
koder_agent/config/__init__.py
koder_agent/config/cli_handler.py
koder_agent/config/manager.py
koder_agent/config/models.py
koder_agent/core/__init__.py
koder_agent/core/commands.py
koder_agent/core/interactive.py
koder_agent/core/keyboard_listener.py
koder_agent/core/scheduler.py
koder_agent/core/security.py
koder_agent/core/session.py
koder_agent/core/status_line.py
koder_agent/core/streaming_display.py
koder_agent/core/usage_tracker.py
koder_agent/mcp/__init__.py
koder_agent/mcp/cli_handler.py
koder_agent/mcp/server_config.py
koder_agent/mcp/server_factory.py
koder_agent/mcp/server_manager.py
koder_agent/tools/__init__.py
koder_agent/tools/engine.py
koder_agent/tools/file.py
koder_agent/tools/search.py
koder_agent/tools/shell.py
koder_agent/tools/skill.py
koder_agent/tools/skill_context.py
koder_agent/tools/task.py
koder_agent/tools/todo.py
koder_agent/tools/web.py
koder_agent/utils/__init__.py
koder_agent/utils/client.py
koder_agent/utils/model_info.py
koder_agent/utils/prompts.py
koder_agent/utils/queue.py
koder_agent/utils/sessions.py
koder_agent/utils/terminal_theme.py
koder-0.4.11.dist-info/METADATA
koder-0.4.11.dist-info/WHEEL
koder-0.4.11.dist-info/entry_points.txt
koder-0.4.11.dist-info/licenses/LICENSE
koder-0.4.11.dist-info/RECORD
