Metadata-Version: 2.4
Name: koder
Version: 0.4.11
Summary: An intuitive AI coding assistant and interactive CLI tool that boosts developer productivity with intelligent automation and context-aware support.
Project-URL: Homepage, https://github.com/feiskyer/koder
Project-URL: Repository, https://github.com/feiskyer/koder
Author: Pengfei Ni
License-File: LICENSE
Keywords: agent,agentic,ai,copilot,litellm,openai,vibe coding
Requires-Python: >=3.10
Requires-Dist: aiosqlite>=0.22.1
Requires-Dist: anthropic>=0.75.0
Requires-Dist: apscheduler>=3.11.2
Requires-Dist: backoff>=2.2.1
Requires-Dist: beautifulsoup4>=4.14.3
Requires-Dist: cryptography>=46.0.3
Requires-Dist: ddgs>=9.10.0
Requires-Dist: fastapi-sso>=0.19.0
Requires-Dist: fastapi>=0.128.0
Requires-Dist: google-cloud-aiplatform>=1.132.0
Requires-Dist: httpx[socks]>=0.28.1
Requires-Dist: litellm>=1.80.11
Requires-Dist: openai-agents[litellm]>=0.6.4
Requires-Dist: openai>=2.14.0
Requires-Dist: orjson>=3.11.5
Requires-Dist: prompt-toolkit>=3.0.52
Requires-Dist: pydantic>=2.12.5
Requires-Dist: pyjwt>=2.10.1
Requires-Dist: pynacl>=1.6.2
Requires-Dist: python-multipart>=0.0.21
Requires-Dist: pyyaml>=6.0.3
Requires-Dist: requests>=2.32.5
Requires-Dist: rich>=14.2.0
Requires-Dist: tiktoken>=0.12.0
Requires-Dist: websockets>=15.0.1
Requires-Dist: whatthepatch>=1.0.7
